kaplanmeier/__init__.py
kaplanmeier/examples.py
kaplanmeier/kaplanmeier.py
kaplanmeier/data/survival_example_data.txt
kaplanmeier/helpers/__init__.py
kaplanmeier/helpers/savefig.py
kaplanmeier-0.2.0.dist-info/LICENSE
kaplanmeier-0.2.0.dist-info/METADATA
kaplanmeier-0.2.0.dist-info/WHEEL
kaplanmeier-0.2.0.dist-info/top_level.txt
kaplanmeier-0.2.0.dist-info/RECORD
