Metadata-Version: 2.1
Name: kaplanmeier
Version: 0.2.0
Summary: Create survival curves using kaplanmeier, the log-rank test and making plots.
Home-page: https://erdogant.github.io/kaplanmeier
Download-URL: https://github.com/erdogant/kaplanmeier/archive/0.2.0.tar.gz
Author: Erdogan Taskesen
Author-email: erdogant@gmail.com
Classifier: Programming Language :: Python :: 3
Classifier: License :: OSI Approved :: MIT License
Classifier: Operating System :: OS Independent
Requires-Python: >=3
License-File: LICENSE
Requires-Dist: matplotlib
Requires-Dist: numpy
Requires-Dist: pandas
Requires-Dist: seaborn
Requires-Dist: lifelines
